parish/__init__.py
parish-0.0.1.dev1.dist-info/LICENSE
parish-0.0.1.dev1.dist-info/METADATA
parish-0.0.1.dev1.dist-info/WHEEL
parish-0.0.1.dev1.dist-info/top_level.txt
parish-0.0.1.dev1.dist-info/RECORD
