Metadata-Version: 2.1
Name: parish
Version: 0.0.1.dev1
Summary: Minimal Reinforcement Learning Framework!
Home-page: https://github.com/nmichlo/parish
Author: Nathan Juraj Michlo
Author-email: NathanJMichlo@gmail.com
License: UNKNOWN
Platform: UNKNOWN
Classifier: License :: OSI Approved :: MIT License
Classifier: Operating System :: OS Independent
Classifier: Programming Language :: Python :: 3.8
Classifier: Programming Language :: Python :: 3.9
Classifier: Programming Language :: Python :: 3.10
Requires-Python: >=3.8
License-File: LICENSE
Requires-Dist: pip (>=21.0)
